<?xml version="1.0" encoding="utf-8"?><Search><pages Count="32"><page Index="1"><![CDATA[4]]></page><page Index="2"><![CDATA[Original Name
                                                         AXEBUG SPACE ADVENTURE




                                                All rights reserved. Published by Axebug Comics.
                               Axebug associated logos are trademarks and/or registered trademarks of Axebug Comics.
                                           Illustration and storytelling were realized by Axebug Comics.



                                                                  ISBN
                                                           978-605-031-407-6



                                                               Third printing
                                                                June 2021



                                                              Printing House
                                          Etkileşim Basım Yayın Tanıtım Eğitim Bilişim Hizmetleri Ltd. Şti.
                                  Zübeyde Hanım Mh. Kâzım Karabekir Cd. Ali Kabakçı İş Mrkz. 85/70 Altındağ, Ankara



                                    No part of this publication may be reproduced, or stored in a retrieval system,
                                  or transmitted in any form or by any means, electronic, mechanical, photocopying,
                                        recording, or otherwise, without written permission of the publisher.
                                          For information regarding permission, write to Axebug Comics.
                                       Attention: Permissions Department, contact@axebug.com, Ankara - TR
                                         Akkent 6 Twins Trade A71 Yenimahalle / ANKARA +90 312 911 06 19















                                                    Copyright © 2020 by AXEBUG COMICS



                                                             www.axebug.com]]></page><page Index="3"><![CDATA[]]></page><page Index="4"><![CDATA[EPISODE 1 - WHAT IS TIME?
                                         22 DAYS AFTER ‘ZZZ55’ LAUNCHING FROM THE ROBUG COLONY


                      IT’S THE                      WE                      THERE
                 22ND DAY OF OUR             COMPLETED 10% OF         ARE SIX DAYS UNTIL
                     JOURNEY.                        IT.                OUR FIRST STOP.




















                        FROM                                  I’M SO                                 BUT IT’S
               NOW ON, WE MUST CHECK                  SICK OF THIS! CHECKING                   THE RIGHT THING TO
                    EVERY MOVE .                           EVERY MOVE...                      DO. ALWAYS BE CAREFUL!

















                          SIX EARTH                                         TRANSFER
                      DAYS TO REACH THE                                 THE IMAGE TO THE
                        FIRST POINT...                                   MONITOR, NOW!















                                                                                                             HAH!
                    COME                                         LET’S                                     HAH! HAA!
                   TO ME!                                  SEE... WHO DO WE
                                                             HAVE HERE?
















             4]]></page><page Index="5"><![CDATA[YOU                                  WE HAVE                             REMEMBER,
                WILL REACH THE FIRST                   ONLY FIVE HOURS FOR                  KEEP YOUR EYES WIDE
                 STOP SIX DAYS LATER.                     RESUPPLY THEN!                            OPEN!

















                         YOU WILL                              ACCORDING                        TOTALLY
                REACH THE THIRD STOP MUCH              TO THE COORDINATES, THERE                 RIGHT!
                     EASIER, TRUST ME.               SHOULD BE A WORMHOLE AHEAD.
















                          IS IT                                                                       THEY ARE
                 GOING TO BE A RAT RUN                       AS QUICK                         COSMIC TUNNELS AFTER ALL.
                  WITH THE WORMHOLE?                    AS A FLASH BEETLE!                 THEY EVEN CONNECT THE FURTHEST
                                                                                                POINTS OF THE GALAXY.

















                                                                                                     THAT’S
                             THIS
                                                                                                 LIKE ONE TENTH
                   JOURNEY WAS SUPPOSE TO
                                                                                            SHORTER THAN THE ACTUAL
                        TAKE 1923 DAYS.         THANKS TO THE
                                                                                                      TRIP.
                                              WORMHOLE, IT TAKES
                                                   220 DAYS.














                                                                                                                           5]]></page><page Index="6"><![CDATA[DUE TO MY                            WHAT                                  IF I DO
                CALCULATIONS, THE TRIP IS            ABOUT COMING BACK?                        THE MATH....
                      90% SHORTER.                                                                          COMING BACK
                                                                                                             WILL BE 82%
                                                                                                              SHORTER.















                    YOU                                                       THIS
              ARE A WISE LADY.                                          ONE HAS BRAINS!



















                    MATH IS                                                                          AFTER
                  LIFE, INDEED.                       MATH                                      YOU LEAVE THE
                                                   IS A WAY TO                           WORMHOLE, YOU SHOULD LAND
                                              UNDERSTAND UNIVERSE.
                                                                                              TO YOUR THIRD STOP.

















                       YOU                                HEADS                                    THE
                  HAVE 7 HOURS                        UP OVER HERE!                              AREA OF
                 BEFORE TAKE OFF.                                                              BOSSROACH!


















             6]]></page><page Index="7"><![CDATA[EXACTLY
                       WE WILL                                                      THAT’S                      THAT’S
                 PROBABLY BE AT THE             72 DAYS AND 12               ANOTHER HALF DAY TO            ACCORDING TO
               FOURTH STOP ON DAY 72.            HOURS LATER.                    COUNT, LADY.             THE EARTH, BEETLE.



















                       OH, YES. I                                                                    THE
                WANTED TO ENLIGHTEN                                  SPACE                        THEORY OF
                   YOU ABOUT THIS.                                  AND TIME.                     RELATIVITY!

















                                                             AND DO                                 IF YOU’RE
                          THE                        YOU THINK MATHS AND                    SMART AND BRAVE ENOUGH,
                 POWER OF MATHS AND                PHYSICS WILL SAVE US FROM                   WHAT CAN STOP YOU?
               PHYSICS ARE EVERYWHERE.
                                                      GANSTER BOSSROACH?


















                        I DON’T                     NOTHING,                       LET’S
                 KNOW. WHAT CAN STOP           WITHOUT HESITATION!          NOT MAKE A FUSS...             BEETLE,
                         ME?                 YOU WILL GO THE WHOLE                                    EVERY CLOUD HAS A
                                                   NINE YARDS!                                           SILVER LINING.
















                                                                                                                           7]]></page><page Index="8"><![CDATA[WE ARE                     AREN’T                                          HE
                     NOT SCARED OF HIM!                 WE?                                     SHOULD BE SCARED
                                                                                                      OF US!
















                          ALL                                      SCIENCE                               COURAGE
                  GREAT MINDS RUN IN                        AND KNOWLEDGE WILL                     AND WORKING HARD IS
               THE SAME CHANNEL, RIGHT?                      ACHIEVE EVERYTHING!                   ESSENTIAL OF COURSE.





















                                                     AND                                               SCIENCE,
                 DICIPLINARY                  ALL THAT REQUIRES                                KNOWLEDGE, COURAGE,
                   IS VITAL.                      PATIENCE.                                  HARDWORKING, DICIPLINARY,
                                                                                                     PATIENCE…















                     AND
                   ME! I AM
                ESSENTIAL TOO.
















             8]]></page><page Index="9"><![CDATA[WHAT IS
                                                             NOW,
                       WE WILL                                                               TIME?
                                                        AS I WAS SAYING.
                  CROSS THAT BRIDGE
                                                        TIME AND SPACE.
                 WHEN WE COME TO IT.












                                                      HOW IS
                      DOES IT                TIME FLOWING EVER GOING                WHAT
                TICK DIFFERENTLY TO           TO MAKE SENSE TO US?            DOES IT ALL MEAN?
                     EVERYONE?















                                                           CAN
                        EASY PEASY.
                  THAT’S SOMETHING WHICH           YOU SLOW IT DOWN?
                  EARTH AND SUN CREATES.
                                                                 OR CAN YOU MAKE
                                                                    IT FASTER?
                                                                                                                NO.
















                       IT’S                                                                         IT IS
                                                           I
                   SPECIFIC TO                                                                STILL SOMETIMES.
                                                      THINK NOT!
                    EVERYONE.                                                                                    WHAT
                                                                                                             ARE YOU GOING
                                                                                                            TO SAY TO THAT?


















                                                                                                                           9]]></page><page Index="10"><![CDATA[EPISODE 2 - THEORY OF RELATIVITY
                     THAT’S                                    NO,                                      LET
                  WHAT WE CALL                            THAT DOESN’T                             THE MAN SPEAK
                   RELATIVITY.                            RING A BELL.                                BEETLE.
















                         TIME                                           AND                       RIGHT!
                  CHANGES ACCORDING                              ALL THAT REQUIRES                         I THINK IT’S NOT
                TO PLACE AND MOTIONS.                                 PATIENCE.                           ABOUT THE FLOW

                                                                                                              OF TIME.














                           SO DOES                              THAT                             FEELING
                     IT CHANGE ACCORDING                  SOUNDS CORRECT.                      THE TIME…
                        TO HOW I FEEL?


















                    TIME                                                                                   THEN
             CHANGES ACCORDING                           YEAH.                                        TIME WILL MAKE
                   TO OUR SENSES.                                                                   A MASSIVE CHANGE IN
                                                                                                      UNIVERSAL SCALE.
                                 RIGHT?







                                                   FOR
                                                   SURE.









             10]]></page><page Index="11"><![CDATA[FIRST                               THERE ARE                             WE
                     THING IS FIRST. HOW                 DOZENS OF WAYS USED IN                 MEASURED THE
                    DO WE MEASURE TIME?                          HISTORY.                    EARTH’S TURN, RIGHT?


















                          THE                                    OR WE                                  WHAT?
                EARTH TURNS AROUND IT’S                    DIVIDED IT INTO 24
                    AXIS IN 24 HOURS.                           HOURS…

















                      WHY ARE                         THEN,                    SO WE
                 YOU SHOCKED? I JUST               AN HOUR IS 60           DIVIDED 1 HOUR
               GAVE A SECOND OPINION.                MINUTES.                 INTO 60.




















                       GREAT!                         WE                              WE                       I HAVE
                NOW YOU ARE LOOKING            DIVIDED A MINUTE                   SAID THAT 60             NEVER SEEN IT
               FROM ANOTHER POINT OF         INTO 60 AND CALLED IT              SECONDS MAKE A             FROM THIS SIDE.
                      VIEW TOO.
                                                   SECONDS.                         MINUTE.
















                                                                                                                           11]]></page><page Index="12"><![CDATA[WHAT                          EARTH
                     ABOUT YEAR AND                  TURNS AROUND                         AND THEN,
                      MONTH, BEETLE?             THE SUN IN 12 PARTS. WE           WE DIVIDED EVERY PART TO
                                                 CALL MONTH TO EACH OF            30. WE NAMED IT A DAY. THIS
                                                         THEM.                      HELPED US UNDERSTAND
                                                                                             TIME.













                                                     THEN,
                       WE                         TIME FLOWS                                                 BUT IT
                   DON’T HAVE A              EXACTLY THE SAME FOR            YEAH.                    CHANGES ACCORDING
               CHANCE OF SLOWING            EVERYBODY AROUND THE                                      TO PEOPLE’S MOTIONS.
                  EARTH’S TURN.                     WORLD.















                      I WONDER                            WELL,                  THAT’S
                 WHAT MEASURES TIME                     CLOCKS OF                    RIGHT!
                      THE BEST?                          COURSE.
                                                                                     BUT WHICH ONE
                                                                                  MEASURES THE BEST?


















                         THE                                                       IT
                   BEST MEASURE IS                                         VIBRATES 9 BILLION            WOW,
               THE VIBRATION OF CESIUM                                     TIMES PER SECOND.         THAT’S A LOT!
                      ELEMENT.

















             12]]></page><page Index="13"><![CDATA[I LOVE CHEMISTRY !







                                                                                                                           13]]></page><page Index="14"><![CDATA[I WAS
                                                                IT IS                WONDERING IF THERE
                                                         THE MOST ACCURATE        IS A RELATIONSHIP BETWEEN
                     CESIUM’S                                 MEASURE.            OUR SHIPS NAME AND ATOMIC
               ATOMIC NUMBER IS 55.
                                                                                      NUMBER OF CESIUM?
                                        IT’S IN
                                    1A GROUP, THE
                                   6TH PERIOD. IT HAS
                                         55…

                                          WAIT A
                                         MINUTE!
                                                                     YES.
                                                               YOU ARE A SMART
                                                                  ONE, LADY.










                        WHEN I                               I ADDED
                 WAS BUILDING `ZZZ55’,               CESIUM’S ATOMIC NUMBER
              MY DREAM WAS TO TRAVEL IN                 TO MY SHIP’S NAME.
                    SPACE AND TIME.

















                         AND                                                                                  EARTH’S
                THE LOGO OF MY SHIP IS                                                                   AXIS TILT IS 23° 27.
              WRITTEN WITH A 55 DEGREED
                        ANGLE!















                     WHAT                                            LET’S                   GEOMETRY
                 DOES THAT EVEN                              MOVE INTO GEOMETRY!         IS ALL AROUND THE
                     MEAN?                                                                    UNIVERSE!














             14]]></page><page Index="15"><![CDATA[IT’S A
                         `AEI                   WHICH                     LATIN PHRASE.                CHEMISTRY...
                       HOTHEAS               LANGUAGE IS                                PLATO.
                      GEOMETRY!’                THAT?                                                          GEOMETRY...
                                                                                                                      PLATO...
















                   WHAT                       PLATO                            HE                            AND
                 IS PLATO?            WAS A PHILOSOPHER IN               ESTABLISHED THE              NAMED IT ‘ACADEMY’.
                                         ANCIENT GREECE.                   UNIVERSITY.















                                                               OK. PUT                                           YEAH,
                       YES, WOW.                       55 IN THE POCKET. WHAT                               WHAT DOES THAT
                                                            ABOUT ZZZ?                                        STAND FOR?
                             I ALWAYS
                          WONDERED ABOUT WHY
                         THE SHIP IS NAMED `ZZZ55.’















                     CAN                  OR                                       OR                         WHAT
                 IT BE ZEUS’S          THE ZOO?              OR                  ZOOM?                    ABOUT ZODIAC?
             NAME, WHICH IS AKA                             ZERO?
                  JUPITER?







                   CAN IT                Z FOR                 Z FOR                  Z                    Z FOR
               BE Z FOR ZEG?         THE LETTER Z?             ZIPPY?            FOR ZENITH?             ZEPPELIN?









                                                                                                                           15]]></page><page Index="16"><![CDATA[BUT
                    ZZZ55 LOOKS LIKE AN                       INDEED,                       ANYWAY, GET BACK
                    ENOURMOUS HOUSEFLY.                 IT WAS INSPIRED BY A                    TO OUR BUSINESS.
                                                             HOUSEFLY.
                                                                                                          SPACE AND TIME.















                             WHAT DID                             WHAT DID                         GRAVITATIONAL
                       EINSTEIN TRY TO SAY IN            HE TRY TO SAY, ANSWER HIM?              FORCE EFFECT TIME.
                       HIS SPACETIME THEORY?
















                      SO, THAT                       I DON’T                                             EINSTEIN’S
                      WAS ALL?                       GET IT!                                       THEORY OF RELATIVITY
                                                                                                  SAYS THAT GRAVITY CAN
                                                                                                        BEND TIME.


















                                 ACCORDING                                                  OK…                  BLACK
                           TO EINSTEIN, TIME RUNS                                           FOR                HOLES, FOR
                      SLOWER WHEN GRAVITIONAL FORCE                                      INSTANCE…              INSTANCE.
                                 INCREASES.

















             16]]></page><page Index="17"><![CDATA[IMAGINE
                   WE HAVE A SHIP AND
                      A BLACKHOLE.
































                                                                                                 SINGULARITY





                                                                                                     EVENT
                                                                                                   HORIZON












                                                                                                   ACRETION DISC




                                                                    PICTURE                         WHEN
                           AND ALSO                                                            WE ARE NEAR THE
                    IMAGINE THAT THERE IS A                    TURNING AROUND                BLACK HOLE WITH OUR
                  TWIN OF OUR SHIP, ON EARTH.              THE BLACK HOLE WITHOUT
                                                             ENTERING IT’S GRAVITY          SHIP, TIME WILL BE VERY
                                                                     ZONE.                          SLOW.

















                                                                                                                           17]]></page><page Index="18"><![CDATA[OUR                             OUR
                 HEART RATE WILL SLOW           METABOLISM WILL SLOW                      EVEN OUR
                         DOWN.
                                                         DOWN.                        MOTIONS WILL BE        BUT, IT WON’T
                                                                                        SLOWER THAN          TROUBLE US.
                                                                                           USUAL.














                    JUST                          WE
               LIKE DUCKS IN A             WILL FEEL NATURAL                    UNTIL                       THE
                    ROW.                                                  WE COMPLETE OUR             TWIN WILL GROW
                                         AND VERY ORDINARY IN          TRIP AND COME BACK TO        MUCH OLDER THAN US.
                                                ZZZ55.                         EARTH.
















                    THE                     SO IT                        WE WILL                         BECAUSE
                MORE WE STAY           WILL EFFECT THE               BE EFFECTED BUT,                WE ARE NEAR THE
               NEAR THE BLACK          SPEED OF TIME.            IT WILL EFFECT THE TWIN                BLACKHOLE.
            HOLE, THE MUCH TWIN                                       MORE THAN US.
                 WILL GROW.

















                       IT IS A                      THE                            ‘THE                        THE
                 PARADOX AFTERALL.          PARADOX IS CALLED…                                            TWIN PARADOX
                                                                             TWIN PARADOX’.
                                                                                                        TELLS US ABOUT THE
                                                                                                       FLOW OF TIME AND THE
                                                                                                          SPEED OF LIGHT.















             18]]></page><page Index="19"><![CDATA[EPISODE 3 - PINK & FLOYD
                       LET’S
                SAY PINK AND FLOYD
              ARE TWIN BROTHERS. THEY                                                           ONE DAY, PINK
            WERE BORN ON THE SAME DAY                                                          GOES TO SPACE
                     AND TIME.             PINK                                                WITH HIS SPACE
                                           AND                                                     ROCKET.
                                          FLOYD
                                          LIVE ON
                                          EARTH.












                                                                                                        PINK’S
                      AND FLOYD         PINK COMES BACK                                         TIME WATCH WILL TICK
                      STAYS ON           TO EARTH AFTER                                      SLOWER THAN EARTH TIME, AT
                    EARTH, LIVING       TRAVELLING WITH                                           THE SPEED OF 4%.
                       HIS LIFE.         LIGHT SPEED FOR
                                           FIVE YEARS.














                                                                                                            WHILE
                           FLOYD                                 LET’S
                     WILL FEEL LIKE 100                   DO THE MATH. IF PINK                           PINK SPENDS 5
              SECONDS, WHEREAS PINK WILL FEEL        SPENDS 5 YEARS IN SPACE, HOW                   YEARS WITH LIGHT SPEED,
                      LIKE 4 SECONDS.                MUCH TIME WILL PASS FOR FLOYD                   FLOYD WILL SPEND 125
                                                                                                            YEARS.
                                                               ON EARTH?













                        THUS,
                  THE TWIN PARADOX                      WE CAN                                        PEOPLE
                TELLS US THE RELATION            ONLY UNDERSTAND THE                              ON EARTH CAN’T
               BETWEEN SPACE, TIME AND          DIFFERENCE ON UNIVERSAL                       REALIZE THE DIFFERENCE.
                     LIGHT SPEED.                        SCALE.


















                                                                                                                           19]]></page><page Index="20"><![CDATA[LIGHT
                            WHAT IF                     SPEED DOESN’T                                   LIGHT
                     WE SOMEHOW MOVED IN             CHANGE, NO MATTER                            SPEED TRAVELS AT
                         LIGHT SPEED?                       WHAT.                              300.000 KM PER SECOND.
                                                                       IT IS CONSTANT.
















                      WHAT IF                     TIME                                                      I MEAN,
                 WE STABILIZED OUR              WOULD                         WOULD                     THERE WON’T BE
              SPEED TO 300.000 KM PER       DEFINATELY STOP.              IT REALLY STOP?                TIME AT ALL.
                   SECOND THEN?


















                   OR                   THEN…
                WE WOULD                                          IF                       IS IT                 CAN
            JUMP TO ANOTHER                                  TIME STOPS             POSSIBLE TO MOVE        WE TRAVEL IN…
                DIMENSION.                               DURING OUR TRAVEL         FASTER THAN LIGHT?
                                                           IN LIGHT SPEED…















            AND?                   JUST                         I MEAN,
                   A PENNY      SAYING…                      TIME TRAVEL?
                   FOR YOUR
                  THOUGHTS…
                                         CAN WE GO
                                        BACK IN TIME?















             20]]></page><page Index="21"><![CDATA[YES!                                HAVE                     NOPE!
                                                 YOU EVER HEARD                                           IT’S A
                         TIME                OF THE WORD `TACHYON’                                     GREEK WORD.
                      TRAVEL WOULD                   BEFORE?
                       BE POSSIBLE.                                                                               IT MEANS
                                                                                                                    ‘FAST’.















                                                                                   FAST
                  TACHYONS                  THINK                              AS GREASED                    THEN
                ARE PARTICLES            ABOUT THEIR                            LIGHTNING!              WE COULD PASS
                  WHICH ARE                SPEED.                                                   MILLIONS OF WHATEVER
              TRAVELLING FASTER                                                                    LIGHT THERE IS AND REACH
                  THAN LIGHT.                                                                          OTHER GALAXIES.




                                                                         BLAZING
                                                                           FAST.








                         THE                       ANDROMEDA!
                 NEAREST GALAXY TO                                                              YES. THE
                        US IS…                                                            NEAREST GALAXY TO
                                                                                            THE MILKY WAY.
                                                                                                         THE ONE AND ONLY
                                                                                                            ANDROMEDA...













                               IF WE                               WE                            SO WE
                          WERE WATCHING                  WOULD SEE THE IMAGE OF           CAN TRAVEL BACK IN
                          THE EARTH FROM               EARTH FROM 2 MILLION YEARS           TIME, AFTER ALL.
                            ANDROMEDA…                           BEFORE.

















                                                                                                                           21]]></page><page Index="22"><![CDATA[THERE
                  IS A THEORY                       OH, I
              THAT CLARIFIES THE              KNOW! THE THEORY                YEAH!                          E=M.C  2
               RELATION BETWEEN                 OF RELATIVITY.
                SPACE AND TIME.
                                                                                      ALBERT
                                                                                      EINSTEIN.













                                              THEORY                          ARE                        CONSTANT
                   THAT’S                    OF SPECIAL                 THEY HORSE OF A             SPEED AND RELATIVE
                    RIGHT.                 RELATIVITY AND              DIFFERENT COLOUR?                   SPEED.
                                        GENERAL RELATIVITY.














                        THE                            BUT                            WE
                 THEORY OF SPECIAL              GENERAL RELATIVITY             ARE DEALING WITH                RIGHT?
                 RELATIVITY FOCUSES          FOCUSES ON OBJECTS THAT           SPECIAL RELATIVITY
              ON OBJECTS WHICH HAS A        CAUSES SPACETIME TO CURVE                THEN?
                  CONSTANT SPEED.
                                                  AT ANY SPEED.














               YES.                                I                                                          TELL ME
                                          WONDER IF WE CAN                 I DON’T
                    THAT IS             BE FASTER THAN LIGHT              THINK SO.                          WHY NOT?
                      CONSTANT                 SPEED?
                    SPEED, IN OTHER
                     WORDS LIGHT
                        SPEED.


















             22]]></page><page Index="23"><![CDATA[FOR                         AND, IF                  WHAT                         IT WOULD
                       INSTANCE, IF I            IT WAS TRAVELLING         WOULD HAPPEN?               GO WITH LIGHT SPEED.
                  HAD A CAR GOING WITH           AT 300.000 KM PER
                       LIGHT SPEED…                   SECOND…
















                     YEAP!              LET’S                   THE LIGHT                RIGHT?                     YES.
                                     TURN ON THE          WILL BEGIN TO MOVE IN
                                    HEADLIGHTS OF           FRONT OF THE CAR.
                                       THE CAR.













                    I’M                WHICH              BUT                                    FOR
                TURNING ON           GOES WITH        MY CAR CAN’T           SEE?            PITY’S SAKE…
              THE HEADLIGHTS        LIGHT SPEED.      PASS IT’S OWN
                OF MY CAR…           FAST AS A        HEADLIGHTS.                                                  IT’S A
                                      HORSE!                                                                     PARADOX.

















                    WHAT IS                                            OH                   HUSH              PARADOXES
                  A PARADOX?                PARADOX              MY! GREEKS ARE          AND LISTEN!         ARE AGAINST
                                           IS A GREEK             EVERYWHERE!                                STATEMENTS.
                                        WORD. KNOWN AS
                                          ‘PARADOXUS’.



















                                                                                                                           23]]></page><page Index="24"><![CDATA[EPISODE 4- GRAVITATIONAL FORCE
                     GUYS,                                 NOW                               EVEN IF SPACE
               DON’T EVER FORGET                        AS TO YOUR                       AND TIME SEEM TO BE
                     THESE NAMES...                                                            DIFFERENT…
                                                        QUESTION…
                                                                                                         THEY ARE RELATED
                               GALILEO, NEWTON                                                             TO EACH OTHER.
                                AND EINSTEIN.













                                                                                                        TIME
                           THE                                      TIME
                    TIME THAT A PERSON                   SLOWS DOWN FOR OBJECTS                 DILATION DEPENDS ON
                FEELS WHILE STAYING STILL IS          OR PEOPLE WHICH TRAVEL AT LIGHT            THE OBJECTS SPEED.
              DIFFERENT THAN THE TIME THAT A                       SPEED.
               PERSON FEELS WHILE GOING ON
                       LIGHT SPEED.














                      FOR AN
                  OBSERVER, WHILE                            EVERYTHING            ACCORDING                  2
              LOOKING AT A LIGHTSPEED                        WILL BE SEEN            TO THE           E=MC
              TRAVELLING OBJECT, TIME                 NORMAL FOR ANYONE WHO        FORMULA…     ENERGY   EQUALS   MASS
                   WILL BE ZERO.                      TRAVELS WITHIN LIGHTSPEED
                                                               OBJECT.
                                                                                                            TIMES THE SPEED
                                                                                                           OF LIGHT SQUARED.
                                                            IN OTHER
                                                   WORDS, ENERGY AND MASS ARE
                                               INTERCHANGEABLE; THEY ARE DIFFERENT
                                                    FORMS OF THE SAME THING.






                     AND
                  THERE ARE                 NOTRINO.                   WE                    PHYSICS            AMAZING
               PARTICLES GOING          THEY ARE CALLED         ARE DEALING WITH           PLUS MATHS         AS A GHOST!
               THROUGH MATTER.          GHOST PARTICLES.        GHOSTS, AREN’T WE?       EQUALS AMAZING!



















             24]]></page><page Index="25"><![CDATA[LET’S                                     RIGHT?
              GET BACK TO THE              OUR                                           JUST                   OK.
                    CAR.               LIGHTSPEED                                  LIKE DUNG BEETLE
                                     TRAVELLING CAR                             SAID, LET’S TURN ON THE
                                    SIMPLY GOES WITH                                  HEADLIGHTS.
                                    CONSTANT SPEED.




                                                           YES.








                                                                                                   THIS
                                                                                               MEANS THERE
                    WHEN                   WE WILL SEE                                      ARE TWO DIFFERENT
               WE TURN ON THE           DIFFERENT RESULTS                                    ENDINGS TO THIS
                   LIGHTS…             ACCORDING TO WHERE                                         STORY.
                                              WE ARE.

                                                       INSIDE OR OUTSIDE THE
                                                                CAR.

                                                                                             FOR
                                                                                            SURE.








                              LET’S                          THE
                      SEE… WHEN WE ARE IN                LIGHTSPEED                                THE
                            THE CAR…                TRAVELLING CAR GOES                      HEADLIGHTS ONLY
                                                    WITH CONSTANT SPEED.                  LIGHTEN THE FRONT OF
                                                                                                 THE CAR.















                                                                                                 NOW, WE TURN
                       NOW,                              WITH                   WITH          ON THE HEADLIGHTS.
                   LET’S THINK OF                 WHICH SPEED DOES          LIGHT SPEED.
                 OUTSIDE THE CAR.                    THE CAR GO?
                                                                                                             THE PERSON OUTSIDE
                                                                                                             THE CAR CAN’T SEE ANY
                                                                                                               LIGHT IN FRONT OF
                                                                                                                     CAR.













                                                                                                                           25]]></page><page Index="26"><![CDATA[IT
                                HOW                    ALREADY LIGHTENED
                            CAN THAT BE?             THE FRONT OF THE CAR.                                      THAT’S
                                                                                             YES.          WHAT THE DRIVER
                                                                                                                SEES.















                                                                                      CAN                           NO,
                         THE                    HEADLIGHTS                       ANYTHING PASS                    IT CAN’T.
                    CAR IS AT LIGHT          ARE ALSO AT LIGHT                LIGHT SPEED AT ALL?
                        SPEED.                     SPEED.

















                      THEN,                                      SO,                   MAYBE,                    THE
                 THE CAR AND THE            YES.            ACCORDING TO            HE IS BEHIND         GENERAL RELATIVITY
              HEADLIGHTS ARE GOING                       THE PERSON OUTSIDE,         THE CAR, HE       ONLY EXAMINES MOTIONS
               WITH THE SAME SPEED,                   HEADLIGHTS ARE NOT GOING        CAN’T SEE         WHICH CHANGE SPEED.
                      RIGHT?                             IN FRONT OF THE CAR.        PROPERLY.


















                     BUT,                                                  GENERAL                                I
                 LIGHT SPEED IS         YEAP.                       RELATIVITY EXPLAINS US                 GUESS SPECIAL
                    STABLE.                                    BLACK HOLES AND THE EXPANDING          RELATIVITY IS JUST STUCK
                                                                       UNIVERSE MODEL.                   IN CONSTANT SPEED.

















             26]]></page><page Index="27"><![CDATA[GENERAL                                                                SPACE,
                 RELATIVITY TELLS US                             IT                        TIME, BLACK             IT’S
            ABOUT GRAVITIONAL FIELD, TIME                ALSO OPENS UP HOW              HOLE, HYPERNOVA,      JUST TOO MUCH
                  AND THEIR EFFECTS.                  BLACK HOLES OCCUR AFTER              RELATIVITY…          TO SINK IN.
                                                       HYPERNOVA EXPLOSIONS.
















                                                                                                            THE
                         THINK                                                        WHAT            ORANGES COME
                   AS SPACE AS A FLAT                    PUT                       HAPPENED?       CLOSER BECAUSE THEY
                         SHEET.                     TWO ORANGES                                         ARE HEAVY.
                                                        ON IT.














                    WHY IS                           GRAVITATIONAL
                    THAT?                                FORCE.                                                    THEN,
                                                                                                NOPE!            WHAT IS IT?

















                          THEY                         SO                      JACKPOT!
                 CAME CLOSER BECAUSE             THE CELESTIAL             NOT ONLY SPACE…                    THEY
                THEY CURVED THE SHEET.       BODIES ON SPACE COME                                         BEND TIME TOO.
                                           CLOSER TO EACH OTHER BY
                                                CURVING SPACE.


















                                                                                                                           27]]></page><page Index="28"><![CDATA[GRAVITATIONAL FORCE

































                                                                                                       THERE
                                                                                                  ARE MILLIONS OF
                                   YES,                                                          CELESTIAL BODIES IN
                             CELESTIAL BODIES                                                       THE UNIVERSE.
                              BEND TIME TOO.                  AND
                                                        THEY BEND LIGHT                                           SO?
                                                              TOO.



















                                                      THEY                       DO YOU
                       THEY ALL                                             UNDERSTAND WHY                 BECAUSE
                 BEND THE SPACE THAT             BEND TIME AND            WORMHOLES MAKE LIFE          THEY BEND SPACE
                  THEY’RE IN, BEETLE!        SPACE WHILE SPINNING IN          MUCH EASIER?
                                                   THEIR AXIS.                                             AND TIME.


















             28]]></page><page Index="29"><![CDATA[FOR                            WE                                     AND               SLOW?
                     EXAMPLE, IF WE                  NEED TO GO                          THIS PROVES HOW
                   WANTED TO GO TO A              EXACTLY 2 MILLION                     SLOW LIGHT SPEED IS.
              GALAXY 2 MILLION LIGHT YEARS         YEARS FURTHER.
                       FURTHER…
                                                                   ANDROMEDA
                                                                 HOAG - NGC1300
                                                                  M82 - GIROLAP












                       OF                 SO, IT                                          IT’S                  WARP
                 COURSE. LIGHT          IS SLOW…                   YES,              TIME TO TALK            DRIVERS ARE
              SPEED IS NOT ENOUGH                                BEETLE!         ABOUT WARP DRIVERS       MUCH MORE FASTER
                TO EXPLORE THE                                                           THEN.               THAN LIGHT.
                   UNIVERSE.
















                                                                                                            SO WE
                                                                                                       CAN MOVE FASTER
                           IT’S                                                                      THAN LIGHT IN HYPER
                     CALLED `FASTER                                                                         SPACE.
                       THAN LIGHT’.


















                   SO,                      BEING                       SO WE                              WE WILL
               WHAT’S THE             FAST IS AWESOME,             CAN REACH DEEP                    LAND TO THE SECOND
                  POINT?           WE DON’T WASTE TIME ON        SPACE AND GALAXIES.                STOP IN THIRTY MINUTES.
                                          THE WAY.















                                                                                                                           29]]></page><page Index="30"><![CDATA[YOU                                               3RD
                        HAVE REACHED THE                                 CAPTAIN. CHECKINGS
                  SECOND LOCATION. BE AWARE OF                            ARE DONE, RIGHT?
                         BOSSROACH. OVER!





                                                                                                ALL
                                                                                          CHECKINGS ARE
                                                                                               DONE!

                    2ND                                 READY!
                CAPTAIN. ARE
                                                                                                   WE
                 WE READY?
                                                                                             WILL TAKE OFF 5
                                                                                              HOURS LATER.
                                                                               SURFACE                          KEEP
                                                                           SCAN IS POSITIVE.               YOUR EYES WIDE
                                                                                                                OPEN!


                                                                             SCAN
                                                                          URGENTLY!






                        LET’S
                LAND TO THE SECOND
            STOP. SEARCH FOR THE SURFACE
                AS SOON AS WE LAND.


               UNDERSTOOD!
                                                                                                                    M38





             30                                                                                              END OF CHAPTER 4]]></page><page Index="31"><![CDATA[SPACE ADVENTURE




































































                                                                                                                  H  A P T E
                                                                                                                 C           R
                                                                                                                     5]]></page><page Index="32"><![CDATA[COME             YOU
             ANOTHER POINT IN                                                     CLOSER.         LITTLE…        CREATURES.
                 DEEP SPACE...


















                                                                                     LET’S
                                                                                   HEAR THE
                                                                                   SENSORS!



















                        I AM                                    OF
                TRANSFERRING THEIR                       COURSE YOU ARE
                   CONVERSATION.                     GOING TO KEEP YOUR EYES
                                                            WIDE OPEN.














                                                                                                    TAKE
                  LOCK                                           AYE                             YOUR LAST
              THEM AS SOON               DID                 AYE GANSTER                     BREATHS. FIVE HOURS
            AS THEY TAKE OFF!       YOU GET THAT       BOSSROACH! I’M GOING TO               LATER, YOU WILL BE
                                     FIBER HORN?        LOCK THEM IN NO TIME!                    DESTROYED!
                                                                            ALL                                   HA HA
                                                                       PREPARATIONS
                                                                         ARE READY.                                 HA!















                                                                                                              TO BE CONTINUED...]]></page></pages></Search>