{
    "result": [
        [
            [
                {
                    "student": "TEMPLATE",
                    "answer": "D",
                    "weigth": 1,
                    "score": 0,
                    "method": "",
                    "function": "E1",
                    "functionScore": false
                },
                {
                    "student": "",
                    "answer": "D",
                    "weigth": 2,
                    "score": 0,
                    "method": "",
                    "function": "E10",
                    "functionScore": false
                },
                {
                    "student": "",
                    "answer": "A",
                    "weigth": 2,
                    "score": 0,
                    "method": "",
                    "function": "E10",
                    "functionScore": false
                },
                {
                    "student": "",
                    "answer": "B",
                    "weigth": 2,
                    "score": 0,
                    "method": "",
                    "function": "E10",
                    "functionScore": false
                },
                {
                    "student": "",
                    "answer": "D",
                    "weigth": 2,
                    "score": 0,
                    "method": "",
                    "function": "E10",
                    "functionScore": false
                },
                {
                    "student": "",
                    "answer": "C",
                    "weigth": 2,
                    "score": 0,
                    "method": "",
                    "function": "E10",
                    "functionScore": false
                }
            ],
            [
                {
                    "student": "TEMPLATE",
                    "answer": "D",
                    "weigth": 1,
                    "score": 0,
                    "method": "",
                    "function": "E1",
                    "functionScore": false
                },
                {
                    "student": "",
                    "answer": "lost",
                    "weigth": 4,
                    "score": 0,
                    "method": "",
                    "function": "E6",
                    "functionScore": false
                },
                {
                    "student": "",
                    "answer": "gap",
                    "weigth": 3,
                    "score": 0,
                    "method": "",
                    "function": "E6",
                    "functionScore": false
                },
                {
                    "student": "",
                    "answer": "figure out",
                    "weigth": 3,
                    "score": 0,
                    "method": "",
                    "function": "E6",
                    "functionScore": false
                },
                {
                    "student": "",
                    "answer": "crystal",
                    "weigth": 3,
                    "score": 0,
                    "method": "",
                    "function": "E6",
                    "functionScore": false
                },
                {
                    "student": "",
                    "answer": "departure",
                    "weigth": 3,
                    "score": 0,
                    "method": "",
                    "function": "E6",
                    "functionScore": false
                },
                {
                    "student": "",
                    "answer": "five",
                    "weigth": 3,
                    "score": 0,
                    "method": "",
                    "function": "E6",
                    "functionScore": false
                },
                {
                    "student": "",
                    "answer": "artificial",
                    "weigth": 3,
                    "score": 0,
                    "method": "",
                    "function": "E6",
                    "functionScore": false
                },
                {
                    "student": "",
                    "answer": "signal",
                    "weigth": 3,
                    "score": 0,
                    "method": "",
                    "function": "E6",
                    "functionScore": false
                },
                {
                    "student": "",
                    "answer": "launch",
                    "weigth": 3,
                    "score": 0,
                    "method": "",
                    "function": "E6",
                    "functionScore": false
                }
            ],
            [
                {
                    "student": "TEMPLATE",
                    "answer": "D",
                    "weigth": 1,
                    "score": 0,
                    "method": "",
                    "function": "E1",
                    "functionScore": false
                },
                {
                    "student": "",
                    "answer": "C",
                    "weigth": 3,
                    "score": 0,
                    "method": "",
                    "function": "E7",
                    "functionScore": false
                },
                {
                    "student": "",
                    "answer": "A",
                    "weigth": 3,
                    "score": 0,
                    "method": "",
                    "function": "E7",
                    "functionScore": false
                },
                {
                    "student": "",
                    "answer": "E",
                    "weigth": 3,
                    "score": 0,
                    "method": "",
                    "function": "E7",
                    "functionScore": false
                },
                {
                    "student": "",
                    "answer": "B",
                    "weigth": 3,
                    "score": 0,
                    "method": "",
                    "function": "E7",
                    "functionScore": false
                },
                {
                    "student": "",
                    "answer": "D",
                    "weigth": 3,
                    "score": 0,
                    "method": "",
                    "function": "E7",
                    "functionScore": false
                }
            ],
            [
                {
                    "student": "TEMPLATE",
                    "answer": "D",
                    "weigth": 1,
                    "score": 0,
                    "method": "",
                    "function": "E1",
                    "functionScore": false
                },
                {
                    "student": "",
                    "answer": "engine",
                    "weigth": 1,
                    "score": 0,
                    "method": "",
                    "function": "E6",
                    "functionScore": false
                },
                {
                    "student": "",
                    "answer": "otherwise",
                    "weigth": 1,
                    "score": 0,
                    "method": "",
                    "function": "E6",
                    "functionScore": false
                },
                {
                    "student": "",
                    "answer": "board",
                    "weigth": 1,
                    "score": 0,
                    "method": "",
                    "function": "E6",
                    "functionScore": false
                },
                {
                    "student": "",
                    "answer": "total",
                    "weigth": 1,
                    "score": 0,
                    "method": "",
                    "function": "E6",
                    "functionScore": false
                },
                {
                    "student": "",
                    "answer": "departure",
                    "weigth": 1,
                    "score": 0,
                    "method": "",
                    "function": "E6",
                    "functionScore": false
                },
                {
                    "student": "",
                    "answer": "task",
                    "weigth": 1,
                    "score": 0,
                    "method": "",
                    "function": "E6",
                    "functionScore": false
                },
                {
                    "student": "",
                    "answer": "assist",
                    "weigth": 1,
                    "score": 0,
                    "method": "",
                    "function": "E6",
                    "functionScore": false
                },
                {
                    "student": "",
                    "answer": "straight",
                    "weigth": 1,
                    "score": 0,
                    "method": "",
                    "function": "E6",
                    "functionScore": false
                }
            ],
            [
                {
                    "student": "TEMPLATE",
                    "answer": "D",
                    "weigth": 1,
                    "score": 0,
                    "method": "",
                    "function": "E1",
                    "functionScore": false
                },
                {
                    "student": "",
                    "answer": "I ASKED YOU HOW?",
                    "weigth": 9,
                    "score": 0,
                    "method": "",
                    "function": "E7",
                    "functionScore": false
                },
                {
                    "student": "",
                    "answer": "YOU'RE THINKING VERY STRAIGHT.",
                    "weigth": 10,
                    "score": 0,
                    "method": "",
                    "function": "E7",
                    "functionScore": false
                },
                {
                    "student": "",
                    "answer": "THE TARGET BEFORE WE FLY.",
                    "weigth": 9,
                    "score": 0,
                    "method": "",
                    "function": "E7",
                    "functionScore": false
                },
                {
                    "student": "",
                    "answer": "MY FAVORITE TIME!",
                    "weigth": 9,
                    "score": 0,
                    "method": "",
                    "function": "E7",
                    "functionScore": false
                }
            ]
        ]
    ]
}